aionix/__init__.py
aionix/__init__.pyi
aionix/_aionix.abi3.so
aionix/py.typed
aionix_sdk_python-0.1.2.dist-info/METADATA
aionix_sdk_python-0.1.2.dist-info/WHEEL
aionix_sdk_python-0.1.2.dist-info/RECORD
