Metadata-Version: 2.4
Name: aionix-sdk-python
Version: 0.1.2
Classifier: Development Status :: 4 - Beta
Classifier: Intended Audience :: Developers
Classifier: License :: OSI Approved :: Apache Software License
Classifier: Programming Language :: Python :: 3
Classifier: Programming Language :: Python :: 3.9
Classifier: Programming Language :: Python :: 3.10
Classifier: Programming Language :: Python :: 3.11
Classifier: Programming Language :: Python :: 3.12
Classifier: Programming Language :: Python :: 3.13
Classifier: Programming Language :: Rust
Classifier: Topic :: Software Development :: Libraries :: Python Modules
Classifier: Typing :: Typed
Summary: AionixOne Python SDK - High-performance serverless platform client
Keywords: aionix,aionixone,sdk,serverless,workflow,automation,agent,openact,credvault
Author-email: AionixOne Team <contact@aionixone.com>
License: Apache-2.0
Requires-Python: >=3.9
Project-URL: Changelog, https://github.com/aionix-labs/aionix-sdk-python/blob/main/CHANGELOG.md
Project-URL: Documentation, https://docs.aionix.one/sdk/python
Project-URL: Homepage, https://aionix.one
Project-URL: Repository, https://github.com/aionix-labs/aionix-sdk-python
